aerokit/__init__.py
aerokit/aero/CompressibleFlow.py
aerokit/aero/Fanno.py
aerokit/aero/Isentropic.py
aerokit/aero/IterativeSolve.py
aerokit/aero/MassFlow.py
aerokit/aero/Propulsion.py
aerokit/aero/Rayleigh.py
aerokit/aero/ShockWave.py
aerokit/aero/Supersonic.py
aerokit/aero/ThermoKerosen.py
aerokit/aero/ThermoRealGas.py
aerokit/aero/__init__.py
aerokit/aero/degree.py
aerokit/aero/model1D.py
aerokit/aero/nozzle.py
aerokit/aero/refstate.py
aerokit/aero/riemann.py
aerokit/aero/unsteady1D.py
aerokit/aero/plot/__init__.py
aerokit/aero/plot/defaultstyle.py
aerokit/aero/plot/isentropicpolar.py
aerokit/aero/plot/shockpolar.py
aerokit/common/__init__.py
aerokit/common/_dev.py
aerokit/common/_ode.py
aerokit/common/defaultgas.py
aerokit/common/dicovar.py
aerokit/common/extendvar.py
aerokit/common/numspectral.py
aerokit/engine/Cycle_Turbofan.py
aerokit/engine/__init__.py
aerokit/engine/gasgenerator.py
aerokit/engine/propu_be.py
aerokit/engine/propu_be_double_corps.py
aerokit/engine/turbofan.py
aerokit/engine/turbojet.py
aerokit/instance/nozzle.py
aerokit/instance/riemann.py
aerokit/instance/unsteady_inflow.py
aerokit/stability/Euler.py
aerokit/stability/OrrSommerfeld.py
aerokit/stability/__init__.py
aerokit/stability/_base.py
aerokit-1.2.1.dist-info/LICENSE
aerokit-1.2.1.dist-info/METADATA
aerokit-1.2.1.dist-info/WHEEL
aerokit-1.2.1.dist-info/top_level.txt
aerokit-1.2.1.dist-info/RECORD
