Metadata-Version: 2.1
Name: aerokit
Version: 1.2.1
Summary: Python tools for basic fluid mechanics computations
Author-email: "J. Gressier" <jeremie.gressier@isae-supaero.fr>
License: MIT License
Project-URL: Homepage, https://github.com/jgressier/aerokit
Project-URL: Documentation, https://aerokit.readthedocs.io/en/latest/
Classifier: Development Status :: 3 - Alpha
Classifier: License :: OSI Approved :: MIT License
Classifier: Natural Language :: English
Classifier: Operating System :: OS Independent
Classifier: Programming Language :: Python
Classifier: Programming Language :: Python :: 3.7
Classifier: Programming Language :: Python :: 3.8
Classifier: Programming Language :: Python :: 3.9
Classifier: Programming Language :: Python :: 3.10
Classifier: Programming Language :: Python :: 3.11
Classifier: Intended Audience :: Science/Research
Classifier: Topic :: Scientific/Engineering :: Physics
Classifier: Topic :: Software Development :: Libraries :: Python Modules
Requires-Python: >=3.7
License-File: LICENSE
Requires-Dist: numpy >=1.19.4
Requires-Dist: scipy >=1.5.4
Requires-Dist: matplotlib >=3.2
Provides-Extra: dev
Requires-Dist: pytest >=6.0 ; extra == 'dev'
Requires-Dist: pytest-cov >=2.11.1 ; extra == 'dev'
Requires-Dist: pylint >=2.6.0 ; extra == 'dev'
Provides-Extra: doc
Requires-Dist: mkdocs >=1.1 ; extra == 'doc'
Requires-Dist: mkdocs-material >=6.2.5 ; extra == 'doc'
Requires-Dist: mkdocs-jupyter >=0.15 ; extra == 'doc'
Requires-Dist: markdown-include >=0.6.0 ; extra == 'doc'
Requires-Dist: mkdocs-include-markdown-plugin ; extra == 'doc'
Requires-Dist: mkdocs-exclude ; extra == 'doc'
Requires-Dist: mkdocstrings ; extra == 'doc'
